postman_collection_test_generator/__init__.py
postman_collection_test_generator/generator.py
postman_collection_test_generator-0.1.3.dist-info/METADATA
postman_collection_test_generator-0.1.3.dist-info/WHEEL
postman_collection_test_generator-0.1.3.dist-info/entry_points.txt
postman_collection_test_generator-0.1.3.dist-info/top_level.txt
postman_collection_test_generator-0.1.3.dist-info/RECORD
