Metadata-Version: 2.2
Name: postman-collection-test-generator
Version: 0.1.3
Summary: Um gerador automático de testes BDD a partir de coleções Postman
Home-page: https://github.com/Vilariano/postman-collection-test-generator
Author: Agnaldo Vilariano
Author-email: aejvilariano128l@gmail.com
Classifier: Programming Language :: Python :: 3
Classifier: License :: OSI Approved :: MIT License
Classifier: Operating System :: OS Independent
Requires-Python: >=3.7
Requires-Dist: requests
Requires-Dist: behave
Dynamic: author
Dynamic: author-email
Dynamic: classifier
Dynamic: description
Dynamic: description-content-type
Dynamic: home-page
Dynamic: requires-dist
Dynamic: requires-python
Dynamic: summary
